{
  "effect.echoing.attack.hit": {
    "subtitle": "effect.echoing.attack.hit",
    "sounds": [
      "peculia:echo_attack_hit"
    ]
  },
  "effect.anchored_teleport_fail": {
    "subtitle": "effect.anchored_teleport_fail",
    "sounds": [
      "peculia:fx/anchored/anchored_teleport_fail1",
      "peculia:fx/anchored/anchored_teleport_fail2"
    ]
  },
  "armor.mythril.equip": {
    "subtitle": "armor.mythril.equip",
    "sounds": [
      "peculia:armor/mythril/mythril_equip1",
      "peculia:armor/mythril/mythril_equip2",
      "peculia:armor/mythril/mythril_equip3",
      "peculia:armor/mythril/mythril_equip4",
      "peculia:armor/mythril/mythril_equip5"
    ]
  },

  "armor.moldleap.equip": {
    "subtitle": "armor.moldleap.equip",
    "sounds": [
      "peculia:armor/moldleap/moldleap_equip1",
      "peculia:armor/moldleap/moldleap_equip2",
      "peculia:armor/moldleap/moldleap_equip3",
      "peculia:armor/moldleap/moldleap_equip4",
      "peculia:armor/moldleap/moldleap_equip5",
      "peculia:armor/moldleap/moldleap_equip6"
    ]
  },
  "armor.moldleap.flap": {
    "subtitle": "armor.moldleap.flap",
    "sounds": [
      "peculia:armor/moldleap/flap_1",
      "peculia:armor/moldleap/flap_2",
      "peculia:armor/moldleap/flap_3"
    ]
  },

  "item.echoing_mirror.use": {
    "subtitle": "item.echoing_mirror.use",
    "sounds": [
      "peculia:item/echoing_mirror/echoing_mirror_use1",
      "peculia:item/echoing_mirror/echoing_mirror_use2"
    ]
  },
  "item.healing_tome.use": {
    "subtitle": "item.healing_tome.use",
    "sounds": [
      "peculia:item/healing_tome/use1",
      "peculia:item/healing_tome/use2"
    ]
  },
  "item.healing_tome.crowd_use": {
    "subtitle": "item.healing_tome.crowd_use",
    "sounds": [
      "peculia:item/healing_tome/crowd/use1",
      "peculia:item/healing_tome/crowd/use2"
    ]
  },
  "item.fortifying_tome.use": {
    "subtitle": "item.fortifying_tome.use",
    "sounds": [
      "peculia:item/fortifying_tome/use1",
      "peculia:item/fortifying_tome/use2"
    ]
  },
  "item.fortifying_tome.crowd_use": {
    "subtitle": "item.fortifying_tome.crowd_use",
    "sounds": [
      "peculia:item/fortifying_tome/crowd/use1",
      "peculia:item/fortifying_tome/crowd/use2"
    ]
  },
  "item.empowering_tome.use": {
    "subtitle": "item.empowering_tome.use",
    "sounds": [
      "peculia:item/empowering_tome/use1",
      "peculia:item/empowering_tome/use2"
    ]
  },
  "item.empowering_tome.crowd_use": {
    "subtitle": "item.empowering_tome.crowd_use",
    "sounds": [
      "peculia:item/empowering_tome/crowd/use1",
      "peculia:item/empowering_tome/crowd/use2"
    ]
  },
  "item.agility_tome.use": {
    "subtitle": "item.agility_tome.use",
    "sounds": [
      "peculia:item/agility_tome/use1",
      "peculia:item/agility_tome/use2"
    ]
  },
  "item.agility_tome.crowd_use": {
    "subtitle": "item.agility_tome.crowd_use",
    "sounds": [
      "peculia:item/agility_tome/crowd/use1",
      "peculia:item/agility_tome/crowd/use2"
    ]
  },
  "item.updraft_tome.use": {
    "subtitle": "item.updraft_tome.use",
    "sounds": [
      "peculia:item/updraft_tome/use1",
      "peculia:item/updraft_tome/use2"
    ]
  },
  "item.updraft_tome.crowd_use": {
    "subtitle": "item.updraft_tome.crowd_use",
    "sounds": [
      "peculia:item/updraft_tome/crowd/use1",
      "peculia:item/updraft_tome/crowd/use2"
    ]
  },
  "item.generic_tome.fail": {
    "subtitle": "item.generic_tome.fail",
    "sounds": [
      "peculia:item/generic_tome/fail1",
      "peculia:item/generic_tome/fail2"
    ]
  },
  "item.generic_tome.crowd_fail": {
    "subtitle": "item.generic_tome.fail",
    "sounds": [
      "peculia:item/generic_tome/crowd/fail1",
      "peculia:item/generic_tome/crowd/fail2"
    ]
  },
  "item.watching_tome.use": {
    "subtitle": "item.watching_tome.use",
    "sounds": [
      "peculia:item/watching_tome/use1",
      "peculia:item/watching_tome/use2"
    ]
  },
  "item.harvesting_tome.use": {
    "subtitle": "item.harvesting_tome.use",
    "sounds": [
      "peculia:item/harvesting_tome/use1",
      "peculia:item/harvesting_tome/use2"
    ]
  },
  "item.generic_glyph.use": {
    "subtitle": "item.generic_glyph.use",
    "sounds": [
      "peculia:item/glyph/use1",
      "peculia:item/glyph/use2",
      "peculia:item/glyph/use3"
    ]
  },
  "block.ichor_sticker.release": {
    "subtitle": "block.ichor_sticker.release",
    "sounds": [
      "peculia:block/ichor_sticker/release"
    ]
  },
  "block.perforated_jaw.bite": {
    "subtitle": "block.perforated_jaw.bite",
    "sounds": [
      "peculia:block/perforated_jaw/bite/bite_1",
      "peculia:block/perforated_jaw/bite/bite_2",
      "peculia:block/perforated_jaw/bite/bite_3",
      "peculia:block/perforated_jaw/bite/bite_4",
      "peculia:block/perforated_jaw/bite/bite_5"
    ]
  },
  "block.perforated_jaw.open": {
    "subtitle": "block.perforated_jaw.open",
    "sounds": [
      "peculia:block/perforated_jaw/open/open_1",
      "peculia:block/perforated_jaw/open/open_2",
      "peculia:block/perforated_jaw/open/open_3"
    ]
  },
  "block.fluorite_bricks.place": {
    "sounds": [
      "peculia:block/fluorite_bricks/break1",
      "peculia:block/fluorite_bricks/break2",
      "peculia:block/fluorite_bricks/break3",
      "peculia:block/fluorite_bricks/break4"
    ],
    "subtitle": "subtitles.block.generic.place"
  },
  "block.fluorite_bricks.break": {
    "sounds": [
      "peculia:block/fluorite_bricks/break1",
      "peculia:block/fluorite_bricks/break2",
      "peculia:block/fluorite_bricks/break3",
      "peculia:block/fluorite_bricks/break4"
    ],
    "subtitle": "subtitles.block.generic.break"
  },
  "block.fluorite_bricks.hit": {
    "sounds": [
      "peculia:block/fluorite_bricks/break1",
      "peculia:block/fluorite_bricks/break2",
      "peculia:block/fluorite_bricks/break3",
      "peculia:block/fluorite_bricks/break4"

    ],
    "subtitle": "subtitles.block.generic.hit"
  },
  "block.fluorite_bricks.step": {
    "sounds": [
      "peculia:block/fluorite_bricks/step1",
      "peculia:block/fluorite_bricks/step2",
      "peculia:block/fluorite_bricks/step3",
      "peculia:block/fluorite_bricks/step4",
      "peculia:block/fluorite_bricks/step5",
      "peculia:block/fluorite_bricks/step6"
    ],
    "subtitle": "subtitles.block.generic.footsteps"
  },
  "block.fluorite_bricks.fall": {
    "sounds": [
      "peculia:block/fluorite_bricks/step1",
      "peculia:block/fluorite_bricks/step2",
      "peculia:block/fluorite_bricks/step3",
      "peculia:block/fluorite_bricks/step4",
      "peculia:block/fluorite_bricks/step5",
      "peculia:block/fluorite_bricks/step6"
    ]
  },

  "block.fluorite.place": {
    "sounds": [
      "peculia:block/fluorite/break1",
      "peculia:block/fluorite/break2",
      "peculia:block/fluorite/break3",
      "peculia:block/fluorite/break4"
    ],
    "subtitle": "subtitles.block.generic.place"
  },
  "block.fluorite.break": {
    "sounds": [
      "peculia:block/fluorite/break1",
      "peculia:block/fluorite/break2",
      "peculia:block/fluorite/break3",
      "peculia:block/fluorite/break4"
    ],
    "subtitle": "subtitles.block.generic.break"
  },
  "block.fluorite.hit": {
    "sounds": [
      "peculia:block/fluorite/break1",
      "peculia:block/fluorite/break2",
      "peculia:block/fluorite/break3",
      "peculia:block/fluorite/break4"

    ],
    "subtitle": "subtitles.block.generic.hit"
  },
  "block.fluorite.step": {
    "sounds": [
      "peculia:block/fluorite/step1",
      "peculia:block/fluorite/step2",
      "peculia:block/fluorite/step3",
      "peculia:block/fluorite/step4",
      "peculia:block/fluorite/step5",
      "peculia:block/fluorite/step6"
    ],
    "subtitle": "subtitles.block.generic.footsteps"
  },
  "block.fluorite.fall": {
    "sounds": [
      "peculia:block/fluorite/step1",
      "peculia:block/fluorite/step2",
      "peculia:block/fluorite/step3",
      "peculia:block/fluorite/step4",
      "peculia:block/fluorite/step5",
      "peculia:block/fluorite/step6"
    ]
  },




  "block.mythril.place": {
    "sounds": [
      "peculia:block/mythril/place1",
      "peculia:block/mythril/place2",
      "peculia:block/mythril/place3",
      "peculia:block/mythril/place4",
      "peculia:block/mythril/place5"
    ],
    "subtitle": "subtitles.block.generic.place"
  },
  "block.mythril.break": {
    "sounds": [
      "peculia:block/mythril/break1",
      "peculia:block/mythril/place2",
      "peculia:block/mythril/place4"
    ],
    "subtitle": "subtitles.block.generic.break"
  },
  "block.mythril.hit": {
    "sounds": [
      "peculia:block/mythril/hit1"

    ],
    "subtitle": "subtitles.block.generic.hit"
  },
  "block.mythril.step": {
    "sounds": [
      "peculia:block/mythril/step1",
      "peculia:block/mythril/step2",
      "peculia:block/mythril/step3",
      "peculia:block/mythril/step4",
      "peculia:block/mythril/step5"
    ],
    "subtitle": "subtitles.block.generic.footsteps"
  },
  "block.mythril.fall": {
    "sounds": [
      "peculia:block/mythril/place1",
      "peculia:block/mythril/place2",
      "peculia:block/mythril/place3",
      "peculia:block/mythril/place4",
      "peculia:block/mythril/place5"
    ]
  },


  "block.void_lamp.place": {
    "sounds": [
      "peculia:block/void_lamp/place1",
      "peculia:block/void_lamp/place2",
      "peculia:block/void_lamp/place3",
      "peculia:block/void_lamp/place4",
      "peculia:block/void_lamp/place5"
    ],
    "subtitle": "subtitles.block.generic.place"
  },
  "block.void_lamp.break": {
    "sounds": [
      "peculia:block/void_lamp/break1"
    ],
    "subtitle": "subtitles.block.generic.break"
  },
  "block.void_lamp.hit": {
    "sounds": [
      "peculia:block/void_lamp/hit1"

    ],
    "subtitle": "subtitles.block.generic.hit"
  },
  "block.void_lamp.step": {
    "sounds": [
      "peculia:block/void_lamp/step1",
      "peculia:block/void_lamp/step2",
      "peculia:block/void_lamp/step3",
      "peculia:block/void_lamp/step4",
      "peculia:block/void_lamp/step5"
    ],
    "subtitle": "subtitles.block.generic.footsteps"
  },
  "block.void_lamp.fall": {
    "sounds": [
      "peculia:block/void_lamp/fall1"
    ]
  },

  "block.condensed_void.use": {
    "subtitle": "block.condensed_void.use",
    "sounds": [
      "peculia:block/condensed_void/use1"
    ]
  },

  "block.condensed_void.place": {
    "sounds": [
      "peculia:block/condensed_void/place1",
      "peculia:block/condensed_void/place2",
      "peculia:block/condensed_void/place3",
      "peculia:block/condensed_void/place4",
      "peculia:block/condensed_void/place5"
    ],
    "subtitle": "subtitles.block.generic.place"
  },
  "block.condensed_void.break": {
    "sounds": [
      "peculia:block/condensed_void/break1"
    ],
    "subtitle": "subtitles.block.generic.break"
  },
  "block.condensed_void.hit": {
    "sounds": [
      "peculia:block/condensed_void/hit1"

    ],
    "subtitle": "subtitles.block.generic.hit"
  },
  "block.condensed_void.step": {
    "sounds": [
      "peculia:block/condensed_void/step1",
      "peculia:block/condensed_void/step2",
      "peculia:block/condensed_void/step3",
      "peculia:block/condensed_void/step4",
      "peculia:block/condensed_void/step5"
    ],
    "subtitle": "subtitles.block.generic.footsteps"
  },
  "block.condensed_void.fall": {
    "sounds": [
      "peculia:block/condensed_void/fall1"
    ]
  },

  "block.cryptstone_bricks.place": {
    "sounds": [
      "peculia:block/cryptstone_bricks/place/place1",
      "peculia:block/cryptstone_bricks/place/place2",
      "peculia:block/cryptstone_bricks/place/place3",
      "peculia:block/cryptstone_bricks/place/place4"
    ],
    "subtitle": "subtitles.block.generic.place"
  },
  "block.cryptstone_bricks.break": {
    "sounds": [
      "peculia:block/cryptstone/break/break1",
      "peculia:block/cryptstone/break/break2",
      "peculia:block/cryptstone/break/break3",
      "peculia:block/cryptstone/break/break4",
      "peculia:block/cryptstone/break/break5"
    ],
    "subtitle": "subtitles.block.generic.break"
  },
  "block.cryptstone_bricks.step": {
    "sounds": [
      "peculia:block/cryptstone_bricks/step/step1",
      "peculia:block/cryptstone_bricks/step/step2",
      "peculia:block/cryptstone_bricks/step/step3",
      "peculia:block/cryptstone_bricks/step/step4",
      "peculia:block/cryptstone_bricks/step/step5",
      "peculia:block/cryptstone_bricks/step/step6"
    ],
    "subtitle": "subtitles.block.generic.footsteps"
  },
  "block.cryptstone_bricks.fall": {
    "sounds": [
      "peculia:block/cryptstone/place/place1",
      "peculia:block/cryptstone/place/place2",
      "peculia:block/cryptstone/place/place3",
      "peculia:block/cryptstone/place/place4"
    ]
  },

  "block.cryptstone.place": {
    "sounds": [
      "peculia:block/cryptstone/place/place1",
      "peculia:block/cryptstone/place/place2",
      "peculia:block/cryptstone/place/place3",
      "peculia:block/cryptstone/place/place4"
    ],
    "subtitle": "subtitles.block.generic.place"
  },
  "block.cryptstone.break": {
    "sounds": [
      "peculia:block/cryptstone/break/break1",
      "peculia:block/cryptstone/break/break2",
      "peculia:block/cryptstone/break/break3",
      "peculia:block/cryptstone/break/break4",
      "peculia:block/cryptstone/break/break5"
    ],
    "subtitle": "subtitles.block.generic.break"
  },
  "block.cryptstone.step": {
    "sounds": [
      "peculia:block/cryptstone/step/step1",
      "peculia:block/cryptstone/step/step2",
      "peculia:block/cryptstone/step/step3",
      "peculia:block/cryptstone/step/step4",
      "peculia:block/cryptstone/step/step5",
      "peculia:block/cryptstone/step/step6"
    ],
    "subtitle": "subtitles.block.generic.footsteps"
  },
  "block.cryptstone.fall": {
    "sounds": [
      "peculia:block/cryptstone/place/place1",
      "peculia:block/cryptstone/place/place2",
      "peculia:block/cryptstone/place/place3",
      "peculia:block/cryptstone/place/place4"
    ]
  },


  "block.poprocks.place": {
    "sounds": [
      "peculia:block/poprocks/place1",
      "peculia:block/poprocks/place2",
      "peculia:block/poprocks/place3",
      "peculia:block/poprocks/place4"
    ],
    "subtitle": "subtitles.block.generic.place"
  },
  "block.poprocks.break": {
    "sounds": [
      "peculia:block/poprocks/break1",
      "peculia:block/poprocks/break2",
      "peculia:block/poprocks/break3",
      "peculia:block/poprocks/break4"
    ],
    "subtitle": "subtitles.block.generic.break"
  },
  "block.poprocks.step": {
    "sounds": [
      "peculia:block/poprocks/step1",
      "peculia:block/poprocks/step2",
      "peculia:block/poprocks/step3",
      "peculia:block/poprocks/step4"
    ],
    "subtitle": "subtitles.block.generic.footsteps"
  },
  "block.poprocks.fall": {
    "sounds": [
      "peculia:block/poprocks/place1",
      "peculia:block/poprocks/place2",
      "peculia:block/poprocks/place3",
      "peculia:block/poprocks/place4"
    ]
  },
  "block.poprocks.hit": {
    "sounds": [
      "peculia:block/poprocks/hit1",
      "peculia:block/poprocks/hit2",
      "peculia:block/poprocks/hit3",
      "peculia:block/poprocks/hit4"
    ]
  },
  "music_disc.lulla": {
    "sounds": [
      {
        "name": "peculia:music_disc/lulla",
        "stream": true
      }
    ]
  },
  "entity.ghost.death": {
    "sounds": [
      "peculia:entity/ghost/death1",
      "peculia:entity/ghost/death2"
    ],
    "subtitle": "subtitles.entity.ghost.death"
  },
  "entity.ghost.hurt": {
    "sounds": [
      "peculia:entity/ghost/hurt/hurt1",
      "peculia:entity/ghost/hurt/hurt2"
    ],
    "subtitle": "subtitles.entity.ghost.hurt"
  },
  "entity.ghost.empowered": {
    "sounds": [
      "peculia:entity/ghost/empowered"
    ],
    "subtitle": "subtitles.entity.ghost.empowered"
  },
  "entity.ghost.moan": {
    "sounds": [
      "peculia:entity/ghost/moan/moan1",
      "peculia:entity/ghost/moan/moan2",
      "peculia:entity/ghost/moan/moan3",
      "peculia:entity/ghost/moan/moan4",
      "peculia:entity/ghost/moan/moan5"
    ],
    "subtitle": "subtitles.entity.ghost.moan"
  },
  "entity.ghost.jumpscare": {
    "sounds": [
      "peculia:entity/ghost/jumpscare/jumpscare1",
      "peculia:entity/ghost/jumpscare/jumpscare2",
      "peculia:entity/ghost/jumpscare/jumpscare3",
      "peculia:entity/ghost/jumpscare/jumpscare4"
    ],
    "subtitle": "subtitles.entity.ghost.jumpscare"
  },
  "entity.moldspawn.death": {
    "sounds": [
      "peculia:entity/moldspawn/death/death1",
      "peculia:entity/moldspawn/death/death2",
      "peculia:entity/moldspawn/death/death3",
      "peculia:entity/moldspawn/death/death4",
      "peculia:entity/moldspawn/death/death5"
    ],
    "subtitle": "subtitles.entity.moldspawn.death"
  },
  "entity.moldspawn.hurt": {
    "sounds": [
      "peculia:entity/moldspawn/hurt/hurt1",
      "peculia:entity/moldspawn/hurt/hurt2",
      "peculia:entity/moldspawn/hurt/hurt3"
    ],
    "subtitle": "subtitles.entity.moldspawn.hurt"
  },
  "entity.moldspawn.idle": {
    "sounds": [
      "peculia:entity/moldspawn/idle/idle1",
      "peculia:entity/moldspawn/idle/idle2",
      "peculia:entity/moldspawn/idle/idle3",
      "peculia:entity/moldspawn/idle/idle4"
    ],
    "subtitle": "subtitles.entity.moldspawn.idle"
  },

  "item.hog_horn.stampede": {
    "sounds": [
      "peculia:item/hog_horn/stampede"
    ],
    "subtitle": "subtitles.item.hog_horn"
  },
  "item.hog_horn.pulse": {
    "sounds": [
      "peculia:item/hog_horn/pulse"
    ],
    "subtitle": "subtitles.item.hog_horn"
  },
  "item.hog_horn.cry": {
    "sounds": [
      "peculia:item/hog_horn/cry"
    ],
    "subtitle": "subtitles.item.hog_horn"
  }
}