{
  "parent": "minecraft:adventure/root",
  "criteria": {
    "killed_warden": {
      "conditions": {
        "entity": [
          {
            "condition": "minecraft:entity_properties",
            "entity": "this",
            "predicate": {
              "type": "minecraft:warden"
            }
          }
        ]
      },
      "trigger": "minecraft:player_killed_entity"
    }
  },
  "display": {
    "announce_to_chat": true,
    "description": {
      "translate": "advancements.adventure.kill_warden.description"
    },
    "frame": "task",
    "hidden": true,
    "icon": {
      "item": "minecraft:sculk_shrieker"
    },
    "show_toast": true,
    "title": {
      "translate": "advancements.adventure.kill_warden.title"
    }
  },
  "requirements": [
    [
      "killed_warden"
    ]
  ]
}